<?xml version="1.0" encoding="utf-8"?>
<LanguageData>

  <!-- Anneli_Jurnizia_HikingBoots -->

  <Anneli_Jurnizia_HikingBoots.label>(Jurnizia)2C_HikingBoots</Anneli_Jurnizia_HikingBoots.label>
  <Anneli_Jurnizia_HikingBoots.description>(Jurnizia)2C_HikingBoots</Anneli_Jurnizia_HikingBoots.description>


  <!-- Anneli_Jurnizia_LeatherBoots -->

  <Anneli_Jurnizia_LeatherBoots.label>(Jurnizia)2C_LeatherBoots</Anneli_Jurnizia_LeatherBoots.label>
  <Anneli_Jurnizia_LeatherBoots.description>(Jurnizia)2C_LeatherBoots</Anneli_Jurnizia_LeatherBoots.description>


  <!-- Anneli_Jurnizia_MockbaTrainers_A -->

  <Anneli_Jurnizia_MockbaTrainers_A.label>(Jurnizia)2C_MockbaTrainers_Blue</Anneli_Jurnizia_MockbaTrainers_A.label>
  <Anneli_Jurnizia_MockbaTrainers_A.description>(Jurnizia)2C_MockbaTrainers_Blue</Anneli_Jurnizia_MockbaTrainers_A.description>


  <!-- Anneli_Jurnizia_MockbaTrainers_B -->

  <Anneli_Jurnizia_MockbaTrainers_B.label>(Jurnizia)2C_MockbaTrainers_Black</Anneli_Jurnizia_MockbaTrainers_B.label>
  <Anneli_Jurnizia_MockbaTrainers_B.description>(Jurnizia)2C_MockbaTrainers_Black</Anneli_Jurnizia_MockbaTrainers_B.description>


  <!-- Anneli_Jurnizia_TacticalBoots_A -->

  <Anneli_Jurnizia_TacticalBoots_A.label>(Jurnizia)2C_TacticalBoots_Black</Anneli_Jurnizia_TacticalBoots_A.label>
  <Anneli_Jurnizia_TacticalBoots_A.description>(Jurnizia)2C_TacticalBoots_Black</Anneli_Jurnizia_TacticalBoots_A.description>


  <!-- Anneli_Jurnizia_TacticalBoots_B -->

  <Anneli_Jurnizia_TacticalBoots_B.label>(Jurnizia)2C_TacticalBoots_Tan</Anneli_Jurnizia_TacticalBoots_B.label>
  <Anneli_Jurnizia_TacticalBoots_B.description>(Jurnizia)2C_TacticalBoots_Tan</Anneli_Jurnizia_TacticalBoots_B.description>


</LanguageData>